copilot_proxy/__init__.py
copilot_proxy/__main__.py
copilot_proxy/app.py
copilot_proxy/cli.py
copilot_proxy/config.py
copilot_proxy-0.1.4.dist-info/licenses/LICENSE
copilot_proxy-0.1.4.dist-info/METADATA
copilot_proxy-0.1.4.dist-info/WHEEL
copilot_proxy-0.1.4.dist-info/entry_points.txt
copilot_proxy-0.1.4.dist-info/top_level.txt
copilot_proxy-0.1.4.dist-info/RECORD
