Metadata-Version: 2.4
Name: copilot-proxy
Version: 0.1.4
Summary: GitHub Copilot-compatible proxy for Z.AI GLM coding models
Author: modpotato
License-Expression: MIT
Project-URL: Homepage, https://github.com/modpotato/copilot-proxy
Project-URL: Repository, https://github.com/modpotato/copilot-proxy
Project-URL: Issues, https://github.com/modpotato/copilot-proxy/issues
Keywords: copilot,proxy,fastapi,glm,ollama
Classifier: Development Status :: 4 - Beta
Classifier: Framework :: FastAPI
Classifier: Intended Audience :: Developers
Classifier: Operating System :: OS Independent
Classifier: Programming Language :: Python
Classifier: Programming Language :: Python :: 3
Classifier: Programming Language :: Python :: 3.10
Classifier: Programming Language :: Python :: 3.11
Classifier: Programming Language :: Python :: 3.12
Classifier: Topic :: Internet :: Proxy Servers
Requires-Python: >=3.10
License-File: LICENSE
Requires-Dist: fastapi>=0.110
Requires-Dist: httpx>=0.27
Requires-Dist: uvicorn[standard]>=0.27
Requires-Dist: openai>=1.0.0
Dynamic: license-file
